src/__init__.py
src/codesnippet.py
codesnip-1.0.6.dist-info/LICENSE.txt
codesnip-1.0.6.dist-info/METADATA
codesnip-1.0.6.dist-info/WHEEL
codesnip-1.0.6.dist-info/entry_points.txt
codesnip-1.0.6.dist-info/top_level.txt
codesnip-1.0.6.dist-info/RECORD
