Metadata-Version: 2.1
Name: codesnip
Version: 1.0.6
Summary: A small program for storing and managing your code snippets.
Home-page: https://github.com/sarveshbhatnagar/codesnip
Author: Sarvesh Bhatnagar
Author-email: sarveshbhatnagar08@gmail.com
License: MIT
Keywords: snippet management code save
Platform: UNKNOWN
Classifier: Development Status :: 4 - Beta
Classifier: Intended Audience :: Developers
Classifier: Topic :: Utilities
Classifier: License :: OSI Approved :: MIT License
Classifier: Programming Language :: Python
Classifier: Programming Language :: Python :: 2
Classifier: Programming Language :: Python :: 2.6
Classifier: Programming Language :: Python :: 2.7
Classifier: Programming Language :: Python :: 3
Classifier: Programming Language :: Python :: 3.3
Classifier: Programming Language :: Python :: 3.4
Classifier: Programming Language :: Python :: 3.5
Classifier: Programming Language :: Python :: 3.6
Classifier: Programming Language :: Python :: 3.7
Requires-Dist: pyperclip
